deepfabric/__init__.py
deepfabric/__main__.py
deepfabric/auth.py
deepfabric/builders.py
deepfabric/builders_agent.py
deepfabric/cli.py
deepfabric/cloud_upload.py
deepfabric/config.py
deepfabric/config_manager.py
deepfabric/constants.py
deepfabric/dataset.py
deepfabric/dataset_manager.py
deepfabric/error_codes.py
deepfabric/exceptions.py
deepfabric/factory.py
deepfabric/generator.py
deepfabric/graph.py
deepfabric/hf_hub.py
deepfabric/kaggle_hub.py
deepfabric/loader.py
deepfabric/metrics.py
deepfabric/progress.py
deepfabric/prompts.py
deepfabric/schemas.py
deepfabric/stream_simulator.py
deepfabric/topic_manager.py
deepfabric/topic_model.py
deepfabric/tree.py
deepfabric/tui.py
deepfabric/update_checker.py
deepfabric/utils.py
deepfabric/validation.py
deepfabric/evaluation/__init__.py
deepfabric/evaluation/evaluator.py
deepfabric/evaluation/inference.py
deepfabric/evaluation/metrics.py
deepfabric/evaluation/parser.py
deepfabric/evaluation/backends/__init__.py
deepfabric/evaluation/backends/llm_eval_backend.py
deepfabric/evaluation/backends/ollama_backend.py
deepfabric/evaluation/backends/tool_call_parsers.py
deepfabric/evaluation/backends/transformers_backend.py
deepfabric/evaluation/evaluators/__init__.py
deepfabric/evaluation/evaluators/base.py
deepfabric/evaluation/evaluators/registry.py
deepfabric/evaluation/evaluators/builtin/__init__.py
deepfabric/evaluation/evaluators/builtin/tool_calling.py
deepfabric/evaluation/reporters/__init__.py
deepfabric/evaluation/reporters/base.py
deepfabric/evaluation/reporters/cloud_reporter.py
deepfabric/evaluation/reporters/file_reporter.py
deepfabric/evaluation/reporters/multi_reporter.py
deepfabric/llm/__init__.py
deepfabric/llm/api_key_verifier.py
deepfabric/llm/client.py
deepfabric/llm/errors.py
deepfabric/llm/rate_limit_config.py
deepfabric/llm/rate_limit_detector.py
deepfabric/llm/retry_handler.py
deepfabric/spin/__init__.py
deepfabric/spin/client.py
deepfabric/spin/models.py
deepfabric/tools/__init__.py
deepfabric-4.10.1.dist-info/METADATA
deepfabric-4.10.1.dist-info/WHEEL
deepfabric-4.10.1.dist-info/entry_points.txt
deepfabric-4.10.1.dist-info/licenses/LICENSE
deepfabric-4.10.1.dist-info/RECORD
