Metadata-Version: 2.4
Name: DeepFabric
Version: 4.10.1
Summary: Curate High Quality Datasets, Train, Evaluate and Ship
Author-email: DeepFabric Team <oss@alwaysfurther.ai>
License-File: LICENSE
Requires-Python: >=3.10
Requires-Dist: anthropic>=0.75.0
Requires-Dist: click>=8.1.7
Requires-Dist: componentize-py>=0.19.3
Requires-Dist: datasets<5.0,>=3.0
Requires-Dist: google-api-core>=2.0.0
Requires-Dist: google-genai>=1.56.0
Requires-Dist: huggingface-hub>=1.3.1
Requires-Dist: kagglehub>=0.3.0
Requires-Dist: mermaid-py>=0.8.0
Requires-Dist: ollama>=0.6.1
Requires-Dist: openai>=1.107.2
Requires-Dist: outlines==1.2.9
Requires-Dist: packaging>=25.0
Requires-Dist: posthog>=3.0.0
Requires-Dist: protobuf>=3.20.0
Requires-Dist: pydantic>=2.0.0
Requires-Dist: pyyaml>=6.0.1
Requires-Dist: rich>=13.0.0
Requires-Dist: sentencepiece>=0.1.99
Requires-Dist: spin-sdk>=3.4.1
Requires-Dist: transformers==5.0.0
Provides-Extra: dev
Requires-Dist: bandit>=1.7.10; extra == 'dev'
Requires-Dist: mermaid-py>=0.2.0; extra == 'dev'
Requires-Dist: pytest-cov>=4.0.0; extra == 'dev'
Requires-Dist: pytest-httpx>=0.30.0; extra == 'dev'
Requires-Dist: pytest-mock>=3.10.0; extra == 'dev'
Requires-Dist: pytest>=7.0.0; extra == 'dev'
Requires-Dist: requests-mock>=1.11.0; extra == 'dev'
Requires-Dist: ruff>=0.1.0; extra == 'dev'
Provides-Extra: docs
Requires-Dist: mkdocs-material>=9.0.0; extra == 'docs'
Requires-Dist: mkdocstrings[python]>=0.30.0; extra == 'docs'
Provides-Extra: training
Requires-Dist: accelerate>=0.20.0; extra == 'training'
Requires-Dist: peft>=0.7.0; extra == 'training'
Requires-Dist: torch>=2.4.0; extra == 'training'
Requires-Dist: trl>=0.26.2; extra == 'training'
